[
  {
    "ContainingType": "SalesPrediction.API.Controllers.CustomersController",
    "Method": "GetOrdersByCustomer",
    "RelativePath": "api/Customers/{customerId}/orders",
    "HttpMethod": "GET",
    "IsController": true,
    "Order": 0,
    "Parameters": [
      {
        "Name": "customerId",
        "Type": "System.Int32",
        "IsRequired": true
      }
    ],
    "ReturnTypes": []
  },
  {
    "ContainingType": "SalesPrediction.API.Controllers.CustomersController",
    "Method": "GetCustomerPredictions",
    "RelativePath": "api/Customers/predictions",
    "HttpMethod": "GET",
    "IsController": true,
    "Order": 0,
    "Parameters": [],
    "ReturnTypes": []
  },
  {
    "ContainingType": "SalesPrediction.API.Controllers.EmployeesController",
    "Method": "GetAll",
    "RelativePath": "api/Employees",
    "HttpMethod": "GET",
    "IsController": true,
    "Order": 0,
    "Parameters": [],
    "ReturnTypes": []
  },
  {
    "ContainingType": "SalesPrediction.API.Controllers.OrdersController",
    "Method": "CreateOrder",
    "RelativePath": "api/Orders",
    "HttpMethod": "POST",
    "IsController": true,
    "Order": 0,
    "Parameters": [
      {
        "Name": "dto",
        "Type": "SalesPrediction.Core.DTOs.NewOrderDto",
        "IsRequired": true
      }
    ],
    "ReturnTypes": []
  },
  {
    "ContainingType": "SalesPrediction.API.Controllers.ProductsController",
    "Method": "GetAll",
    "RelativePath": "api/Products",
    "HttpMethod": "GET",
    "IsController": true,
    "Order": 0,
    "Parameters": [],
    "ReturnTypes": []
  },
  {
    "ContainingType": "SalesPrediction.API.Controllers.ShippersController",
    "Method": "GetAll",
    "RelativePath": "api/Shippers",
    "HttpMethod": "GET",
    "IsController": true,
    "Order": 0,
    "Parameters": [],
    "ReturnTypes": []
  }
]